lpjg2nc/__init__.py
lpjg2nc/cdo_interpolation.py
lpjg2nc/count_nans.py
lpjg2nc/file_parser.py
lpjg2nc/grid_utils.py
lpjg2nc/netcdf_converter.py
lpjg2nc2-1.0.0.dist-info/METADATA
lpjg2nc2-1.0.0.dist-info/WHEEL
lpjg2nc2-1.0.0.dist-info/entry_points.txt
lpjg2nc2-1.0.0.dist-info/top_level.txt
lpjg2nc2-1.0.0.dist-info/RECORD
