Metadata-Version: 2.4
Name: lpjg2nc2
Version: 1.0.0
Summary: Convert LPJ-GUESS output files (.out) to NetCDF format
Home-page: https://github.com/JanStreffing/lpjg2nc2
Author: Jan Streffing
Author-email: jan.streffing@awi.de
Project-URL: Documentation, https://lpjg2nc2.readthedocs.io/
Project-URL: Source, https://github.com/JanStreffing/lpjg2nc2
Project-URL: Issues, https://github.com/JanStreffing/lpjg2nc2/issues
Keywords: climate,lpj-guess,netcdf,conversion
Classifier: Development Status :: 5 - Production/Stable
Classifier: Intended Audience :: Science/Research
Classifier: License :: OSI Approved :: GNU General Public License v3 (GPLv3)
Classifier: Programming Language :: Python :: 3
Classifier: Programming Language :: Python :: 3.8
Classifier: Programming Language :: Python :: 3.9
Classifier: Programming Language :: Python :: 3.10
Classifier: Topic :: Scientific/Engineering :: Atmospheric Science
Requires-Python: >=3.8
Requires-Dist: numpy>=1.20.0
Requires-Dist: pandas>=1.3.0
Requires-Dist: xarray>=0.19.0
Requires-Dist: netCDF4>=1.5.7
Requires-Dist: tqdm>=4.61.0
Dynamic: author
Dynamic: author-email
Dynamic: classifier
Dynamic: description
Dynamic: description-content-type
Dynamic: home-page
Dynamic: keywords
Dynamic: project-url
Dynamic: requires-dist
Dynamic: requires-python
Dynamic: summary
